tactigon_gear/__init__.py
tactigon_gear/models.py
tactigon_gear/client/Data_Collection.py
tactigon_gear/client/__init__.py
tactigon_gear/client/models.py
tactigon_gear/client/utilities/Client_Account_Managment.py
tactigon_gear/client/utilities/__init__.py
tactigon_gear/hal/Tactigon_BLE.py
tactigon_gear/hal/__init__.py
tactigon_gear/middleware/Tactigon_Gesture.py
tactigon_gear/middleware/Tactigon_Recorder.py
tactigon_gear/middleware/__init__.py
tactigon_gear/middleware/utilities/Data_Preprocessor.py
tactigon_gear/middleware/utilities/Tactigon_RT_Computing.py
tactigon_gear/middleware/utilities/__init__.py
tactigon_gear-4.1.5.dist-info/LICENSE
tactigon_gear-4.1.5.dist-info/METADATA
tactigon_gear-4.1.5.dist-info/WHEEL
tactigon_gear-4.1.5.dist-info/top_level.txt
tactigon_gear-4.1.5.dist-info/RECORD
