Metadata-Version: 2.1
Name: tactigon-gear
Version: 4.1.5
Summary: Tactigon Gear SDK to connect to Tactigon Skin wereable platform
Author-email: "Next Industries s.r.l" <info@nextind.eu>
Project-URL: Homepage, https://nextind.eu
Classifier: Programming Language :: Python :: 3
Classifier: License :: OSI Approved :: MIT License
Classifier: Operating System :: OS Independent
Requires-Python: >=3.8
License-File: LICENSE
Requires-Dist: requests ==2.31.0
Requires-Dist: scipy ==1.10.1
Requires-Dist: numpy ==1.24.4
Requires-Dist: bleak ==0.21.1
Requires-Dist: scikit-learn ==1.3.1
Requires-Dist: pandas ==2.0.3
